brds/__init__.py
brds/__main__.py
brds/app.py
brds/base.py
brds/cli.py
brds/py.typed
brds/core/__init__.py
brds/core/edit.py
brds/core/environment.py
brds/core/logger.py
brds/core/security.py
brds/core/vault.py
brds/core/crawler/__init__.py
brds/core/crawler/config.py
brds/core/crawler/crawler.py
brds/core/crawler/pipeline_crawl.py
brds/core/crawler/root_crawler.py
brds/core/crawler/templated_url.py
brds/core/crawler/variables.py
brds/core/datasets/__init__.py
brds/core/datasets/dataset_files.py
brds/core/datasets/dataset_info.py
brds/core/datasets/list_datasets.py
brds/core/fetch/__init__.py
brds/core/fetch/fetcher.py
brds/core/fs/__init__.py
brds/core/fs/minio_writer.py
brds/core/fs/reader.py
brds/core/fs/writer.py
brds/core/http/__init__.py
brds/core/http/browser_emulator.py
brds/core/http/client.py
brds/core/http/domain_rate_limiter.py
brds/core/http/url.py
brds/core/importer/__init__.py
brds/core/importer/gunizp_importer.py
brds/core/importer/importer.py
brds/db/__init__.py
brds/db/init_db.py
brds/humanize/__init__.py
brds/humanize/sizes.py
brds/templates/dataset_files.html
brds/templates/datasets.html
brds-0.12.0.dist-info/licenses/LICENSE
brds-0.12.0.dist-info/METADATA
brds-0.12.0.dist-info/WHEEL
brds-0.12.0.dist-info/entry_points.txt
brds-0.12.0.dist-info/top_level.txt
brds-0.12.0.dist-info/RECORD
