Metadata-Version: 2.4
Name: brds
Version: 0.12.0
Summary: Awesome brds created by brahle
Home-page: https://github.com/brahle/brds/
Author: brahle
License-File: LICENSE
Requires-Dist: aiohttp
Requires-Dist: colorama
Requires-Dist: fastapi>=0.94.1
Requires-Dist: html5lib
Requires-Dist: hvac
Requires-Dist: jinja2
Requires-Dist: lxml
Requires-Dist: minio
Requires-Dist: mypy
Requires-Dist: numpy
Requires-Dist: pandas
Requires-Dist: pandas-stubs
Requires-Dist: pyarrow
Requires-Dist: python-dotenv
Requires-Dist: python-json-logger
Requires-Dist: requests
Requires-Dist: types-PyYAML
Requires-Dist: types-requests
Requires-Dist: uvicorn
Provides-Extra: test
Requires-Dist: pytest; extra == "test"
Requires-Dist: flake8; extra == "test"
Requires-Dist: black; extra == "test"
Requires-Dist: isort; extra == "test"
Requires-Dist: mypy; extra == "test"
Requires-Dist: gitchangelog; extra == "test"
Requires-Dist: mkdocs; extra == "test"
Dynamic: author
Dynamic: description
Dynamic: description-content-type
Dynamic: home-page
Dynamic: license-file
Dynamic: provides-extra
Dynamic: requires-dist
Dynamic: summary
